quickdraws/__init__.py
quickdraws/blr.py
quickdraws/correct_for_relatives.py
quickdraws/custom_linear_regression.py
quickdraws/firth_logistic.py
quickdraws/preprocess_phenotypes.py
quickdraws/runRHE.py
quickdraws/scripts/__init__.py
quickdraws/scripts/convert_to_hdf5.py
quickdraws/scripts/quickdraws_step1.py
quickdraws/scripts/quickdraws_step2.py
quickdraws-0.1.5.dist-info/LICENSE
quickdraws-0.1.5.dist-info/METADATA
quickdraws-0.1.5.dist-info/WHEEL
quickdraws-0.1.5.dist-info/entry_points.txt
quickdraws-0.1.5.dist-info/RECORD
