Metadata-Version: 2.3
Name: quickdraws
Version: 0.1.5
Summary: Quickdraws is a software tool for performing Genome-Wide Association Studies (GWAS)
Author: Palamara Lab
Requires-Python: >=3.10,<4.0
Classifier: Programming Language :: Python :: 3
Classifier: Programming Language :: Python :: 3.10
Classifier: Programming Language :: Python :: 3.11
Classifier: Programming Language :: Python :: 3.12
Classifier: Programming Language :: Python :: 3.13
Requires-Dist: bgen_reader (==4.0.8)
Requires-Dist: bitsandbytes ; sys_platform == "linux"
Requires-Dist: h5py
Requires-Dist: joblib
Requires-Dist: numba
Requires-Dist: numpy
Requires-Dist: pandas
Requires-Dist: pybgen
Requires-Dist: pysnptools[bgen] (>=0.5.13)
Requires-Dist: rhe (==1.0.0)
Requires-Dist: scikit_learn
Requires-Dist: scipy
Requires-Dist: statsmodels
Requires-Dist: tables (>=3.10.1,<4.0.0)
Requires-Dist: torch
Requires-Dist: tqdm
Requires-Dist: wandb
